yafowil.widget.richtext-1.6-py3.9-nspkg.pth
yafowil/widget/richtext/__init__.py
yafowil/widget/richtext/example.py
yafowil/widget/richtext/tests.py
yafowil/widget/richtext/widget.py
yafowil/widget/richtext/resources/widget.js
yafowil/widget/richtext/resources/widget_p4.js
yafowil/widget/richtext/resources/widget_p5.js
yafowil/widget/richtext/resources/tinymce/changelog.txt
yafowil/widget/richtext/resources/tinymce/examples/index.html
yafowil/widget/richtext/resources/tinymce/jscripts/tiny_mce/jquery.tinymce.js
yafowil/widget/richtext/resources/tinymce/jscripts/tiny_mce/license.txt
yafowil/widget/richtext/resources/tinymce/jscripts/tiny_mce/tiny_mce.js
yafowil/widget/richtext/resources/tinymce/jscripts/tiny_mce/tiny_mce_popup.js
yafowil/widget/richtext/resources/tinymce/jscripts/tiny_mce/tiny_mce_src.js
yafowil/widget/richtext/resources/tinymce/jscripts/tiny_mce/langs/en.js
yafowil/widget/richtext/resources/tinymce/jscripts/tiny_mce/plugins/advhr/editor_plugin.js
yafowil/widget/richtext/resources/tinymce/jscripts/tiny_mce/plugins/advhr/editor_plugin_src.js
yafowil/widget/richtext/resources/tinymce/jscripts/tiny_mce/plugins/advhr/rule.htm
yafowil/widget/richtext/resources/tinymce/jscripts/tiny_mce/plugins/advhr/css/advhr.css
yafowil/widget/richtext/resources/tinymce/jscripts/tiny_mce/plugins/advhr/js/rule.js
yafowil/widget/richtext/resources/tinymce/jscripts/tiny_mce/plugins/advhr/langs/en_dlg.js
yafowil/widget/richtext/resources/tinymce/jscripts/tiny_mce/plugins/advimage/editor_plugin.js
yafowil/widget/richtext/resources/tinymce/jscripts/tiny_mce/plugins/advimage/editor_plugin_src.js
yafowil/widget/richtext/resources/tinymce/jscripts/tiny_mce/plugins/advimage/image.htm
yafowil/widget/richtext/resources/tinymce/jscripts/tiny_mce/plugins/advimage/css/advimage.css
yafowil/widget/richtext/resources/tinymce/jscripts/tiny_mce/plugins/advimage/img/sample.gif
yafowil/widget/richtext/resources/tinymce/jscripts/tiny_mce/plugins/advimage/js/image.js
yafowil_widget_richtext-1.6.dist-info/licenses/LICENSE.rst
yafowil_widget_richtext-1.6.dist-info/METADATA
yafowil_widget_richtext-1.6.dist-info/WHEEL
yafowil_widget_richtext-1.6.dist-info/entry_points.txt
yafowil_widget_richtext-1.6.dist-info/namespace_packages.txt
yafowil_widget_richtext-1.6.dist-info/top_level.txt
yafowil_widget_richtext-1.6.dist-info/RECORD
